ddf_conversions/__init__.py
ddf_conversions/dir/__init__.py
ddf_conversions/dir/word_to_pdf.py
ddf_conversions/excel_to_change/__init__.py
ddf_conversions/excel_to_change/excel_to_word.py
ddf_conversions-1.0.dist-info/LICENSE
ddf_conversions-1.0.dist-info/METADATA
ddf_conversions-1.0.dist-info/WHEEL
ddf_conversions-1.0.dist-info/top_level.txt
ddf_conversions-1.0.dist-info/RECORD
